spaceopt/__init__.py
spaceopt/optimizer.py
spaceopt/space.py
spaceopt/variable.py
spaceopt-0.2.2.dist-info/LICENSE
spaceopt-0.2.2.dist-info/METADATA
spaceopt-0.2.2.dist-info/WHEEL
spaceopt-0.2.2.dist-info/top_level.txt
spaceopt-0.2.2.dist-info/RECORD
