Metadata-Version: 2.1
Name: spaceopt
Version: 0.2.2
Summary: Hyperparameter optimization via gradient boosting regression
Home-page: https://github.com/ar-nowaczynski/spaceopt
Author: Arkadiusz Nowaczyński
Author-email: ar.nowaczynski@gmail.com
License: MIT
Classifier: License :: OSI Approved :: MIT License
Classifier: Programming Language :: Python :: 3
Classifier: Programming Language :: Python :: 3.7
Classifier: Programming Language :: Python :: 3.8
Classifier: Programming Language :: Python :: 3.9
Requires-Python: >=3.7
License-File: LICENSE
Requires-Dist: lightgbm (>=3.3.0)
Requires-Dist: pandas (>=1.3.0)
